taurus/__init__.py
taurus/_release.py
taurus/_taurushelper.py
taurus/tauruscustomsettings.py
taurus/taurusstatecontroller.py
taurus/cli/__init__.py
taurus/cli/alt.py
taurus/cli/cli.py
taurus/cli/common.py
taurus/cli/test/__init__.py
taurus/cli/test/test_alt.py
taurus/console/__init__.py
taurus/console/enums.py
taurus/console/list.py
taurus/console/table.py
taurus/console/util/__init__.py
taurus/core/__init__.py
taurus/core/release.py
taurus/core/taurusattribute.py
taurus/core/taurusauthority.py
taurus/core/taurusbasetypes.py
taurus/core/taurusconfiguration.py
taurus/core/taurusdatabase.py
taurus/core/taurusdevice.py
taurus/core/taurusexception.py
taurus/core/taurusfactory.py
taurus/core/taurushelper.py
taurus/core/tauruslistener.py
taurus/core/taurusmanager.py
taurus/core/taurusmodel.py
taurus/core/taurusoperation.py
taurus/core/tauruspollingtimer.py
taurus/core/taurusvalidator.py
taurus/core/units.py
taurus/core/epics/__init__.py
taurus/core/epics/__taurus_plugin__
taurus/core/epics/epicsattribute.py
taurus/core/epics/epicsauthority.py
taurus/core/epics/epicsdevice.py
taurus/core/epics/epicsfactory.py
taurus/core/epics/epicsvalidator.py
taurus/core/epics/test/__init__.py
taurus/core/epics/test/test_epicsattribute.py
taurus/core/epics/test/test_epicsvalidator.py
taurus/core/epics/test/res/__init__.py
taurus/core/epics/test/res/epics_test.db
taurus/core/evaluation/__init__.py
taurus/core/evaluation/__taurus_plugin__
taurus/core/evaluation/evalattribute.py
taurus/core/evaluation/evalauthority.py
taurus/core/evaluation/evaldevice.py
taurus/core/evaluation/evalfactory.py
taurus/core/evaluation/evalvalidator.py
taurus/core/evaluation/test/__init__.py
taurus/core/evaluation/test/test_evalattribute.py
taurus/core/evaluation/test/test_evalfactory.py
taurus/core/evaluation/test/test_evalvalidator.py
taurus/core/evaluation/test/res/__init__.py
taurus/core/evaluation/test/res/dev_example.py
taurus/core/evaluation/test/res/ipap_example.py
taurus-5.3.1.dist-info/licenses/LICENSE.txt
taurus-5.3.1.dist-info/METADATA
taurus-5.3.1.dist-info/WHEEL
taurus-5.3.1.dist-info/entry_points.txt
taurus-5.3.1.dist-info/top_level.txt
taurus-5.3.1.dist-info/RECORD
