Metadata-Version: 2.4
Name: taurus
Version: 5.3.1
Summary: A framework for scientific/industrial CLIs and GUIs
Home-page: http://www.taurus-scada.org
Download-URL: http://pypi.python.org/packages/source/t/taurus
Author: Tiago Coutinho et al.
Maintainer: Taurus Community
Maintainer-email: tauruslib-devel@lists.sourceforge.net
License: LGPL
Keywords: CLI,GUI,PyTango,Tango,Shell,Epics
Platform: Linux
Platform: Windows
Classifier: Development Status :: 5 - Production/Stable
Classifier: Environment :: Console
Classifier: Environment :: X11 Applications :: Qt
Classifier: Environment :: Win32 (MS Windows)
Classifier: Intended Audience :: Developers
Classifier: Intended Audience :: Science/Research
Classifier: License :: OSI Approved :: GNU Lesser General Public License v3 or later (LGPLv3+)
Classifier: Natural Language :: English
Classifier: Operating System :: Microsoft :: Windows
Classifier: Operating System :: POSIX
Classifier: Operating System :: POSIX :: Linux
Classifier: Operating System :: Unix
Classifier: Operating System :: OS Independent
Classifier: Programming Language :: Python
Classifier: Programming Language :: Python :: 3.7
Classifier: Programming Language :: Python :: 3.8
Classifier: Programming Language :: Python :: 3.9
Classifier: Programming Language :: Python :: 3.10
Classifier: Programming Language :: Python :: 3.11
Classifier: Programming Language :: Python :: 3.12
Classifier: Programming Language :: Python :: 3.13
Classifier: Topic :: Scientific/Engineering
Classifier: Topic :: Software Development :: Libraries
Classifier: Topic :: Software Development :: User Interfaces
Classifier: Topic :: Software Development :: Widget Sets
Provides: taurus
Requires-Python: >=3.7
License-File: LICENSE.txt
Requires-Dist: numpy>=1.16
Requires-Dist: pint>=0.8
Requires-Dist: click
Requires-Dist: packaging
Requires-Dist: setuptools<81
Provides-Extra: taurus-qt
Requires-Dist: ply>=2.3; extra == "taurus-qt"
Requires-Dist: lxml>=2.1; extra == "taurus-qt"
Requires-Dist: PyQtWebEngine; extra == "taurus-qt"
Requires-Dist: guiqwt>=3; extra == "taurus-qt"
Requires-Dist: pythonqwt<=0.14.3; extra == "taurus-qt"
Provides-Extra: taurus-tango
Requires-Dist: PyTango>=9.2; extra == "taurus-tango"
Provides-Extra: taurus-epics
Requires-Dist: pyepics>=3.2.4; extra == "taurus-epics"
Provides-Extra: taurus-h5file
Requires-Dist: h5py; extra == "taurus-h5file"
Provides-Extra: taurus-qt-editor
Requires-Dist: spyder>=3; extra == "taurus-qt-editor"
Dynamic: author
Dynamic: classifier
Dynamic: description
Dynamic: download-url
Dynamic: home-page
Dynamic: keywords
Dynamic: license
Dynamic: license-file
Dynamic: maintainer
Dynamic: maintainer-email
Dynamic: platform
Dynamic: provides
Dynamic: provides-extra
Dynamic: requires-dist
Dynamic: requires-python
Dynamic: summary
